nmrlineshapeanalyser/__init__.py
nmrlineshapeanalyser/core.py
nmrlineshapeanalyser-0.1.15.dist-info/METADATA
nmrlineshapeanalyser-0.1.15.dist-info/WHEEL
nmrlineshapeanalyser-0.1.15.dist-info/licenses/LICENSE.md
nmrlineshapeanalyser-0.1.15.dist-info/RECORD
