Metadata-Version: 2.4
Name: nmrlineshapeanalyser
Version: 0.1.15
Summary: ss-NMR peak deconvolution and lineshape analysis
Project-URL: Homepage, https://github.com/BiffoQ/nmrlineshapeanalyser
Project-URL: Documentation, https://biffoq.github.io/nmrlineshapeanalyser/
Project-URL: Repository, https://github.com/BiffoQ/nmrlineshapeanalyser.git
Project-URL: changelog, https://github.com/BiffoQ/nmrlineshapeanalyser/blob/main/CHANGELOG.md
Author-email: Abdulkadir Olatunbosun Biffo <biffokadir13@gmail.com>
License-Expression: MIT
License-File: LICENSE.md
Keywords: lineshape analysis,peak deconvolution,ss-NMR
Classifier: Development Status :: 4 - Beta
Classifier: Intended Audience :: Science/Research
Classifier: Operating System :: OS Independent
Classifier: Programming Language :: Python :: 3.10
Classifier: Programming Language :: Python :: 3.11
Classifier: Programming Language :: Python :: 3.12
Classifier: Programming Language :: Python :: 3.13
Classifier: Topic :: Scientific/Engineering :: Chemistry
Classifier: Topic :: Scientific/Engineering :: Physics
Requires-Python: <3.13,>=3.10
Requires-Dist: matplotlib>=3.9.0
Requires-Dist: nmrglue
Requires-Dist: numpy>=1.26.0
Requires-Dist: pandas>=2.2.0
Requires-Dist: scipy
Provides-Extra: dev
Requires-Dist: black>=22.0; extra == 'dev'
Requires-Dist: codecov-cli>=0.4.1; extra == 'dev'
Requires-Dist: isort>=5.0; extra == 'dev'
Requires-Dist: mypy>=0.981; extra == 'dev'
Requires-Dist: pytest>=7.0; extra == 'dev'
Requires-Dist: ruff>=0.0.285; extra == 'dev'
Provides-Extra: docs
Requires-Dist: cairosvg>=2.7.1; extra == 'docs'
Requires-Dist: mkdocs-autorefs; extra == 'docs'
Requires-Dist: mkdocs-gen-files>=0.5.0; extra == 'docs'
Requires-Dist: mkdocs-jupyter; extra == 'docs'
Requires-Dist: mkdocs-literate-nav>=0.6.0; extra == 'docs'
Requires-Dist: mkdocs-material>=9.4.0; extra == 'docs'
Requires-Dist: mkdocs-material[imaging]; extra == 'docs'
Requires-Dist: mkdocstrings[python]>=0.22.0; extra == 'docs'
Requires-Dist: mknotebooks; extra == 'docs'
Requires-Dist: pillow>=10.0.0; extra == 'docs'
Requires-Dist: pymdown-extensions; extra == 'docs'
